walytis_mutability/__init__.py
walytis_mutability/blockstore.py
walytis_mutability/log.py
walytis_mutability/mutablock.py
walytis_mutability/mutablockchain.py
walytis_mutability/utils.py
walytis_mutability-0.1.7.dist-info/METADATA
walytis_mutability-0.1.7.dist-info/WHEEL
walytis_mutability-0.1.7.dist-info/top_level.txt
walytis_mutability-0.1.7.dist-info/RECORD
