Metadata-Version: 2.4
Name: walytis_mutability
Version: 0.1.7
Summary: An overlay for the Walytis blockchain that provides the feature of mutable blocks.
Author: emendir
Requires-Python: >=3.10
Requires-Dist: decorate_all
Requires-Dist: walytis_beta_api
Requires-Dist: walytis_beta_embedded
